AUTHORS.md
LICENSE
README.md
setup.py
hub_li.egg-info/PKG-INFO
hub_li.egg-info/SOURCES.txt
hub_li.egg-info/dependency_links.txt
hub_li.egg-info/entry_points.txt
hub_li.egg-info/requires.txt
hub_li.egg-info/top_level.txt
paddlehub/__init__.py
paddlehub/config.py
paddlehub/env.py
paddlehub/commands/__init__.py
paddlehub/commands/clear.py
paddlehub/commands/config.py
paddlehub/commands/convert.py
paddlehub/commands/download.py
paddlehub/commands/help.py
paddlehub/commands/hub.py
paddlehub/commands/install.py
paddlehub/commands/list.py
paddlehub/commands/run.py
paddlehub/commands/search.py
paddlehub/commands/serving.py
paddlehub/commands/show.py
paddlehub/commands/uninstall.py
paddlehub/commands/utils.py
paddlehub/commands/version.py
paddlehub/commands/tmpl/init_py.tmpl
paddlehub/commands/tmpl/serving_demo.tmpl
paddlehub/commands/tmpl/x_model.tmpl
paddlehub/compat/__init__.py
paddlehub/compat/paddle_utils.py
paddlehub/compat/type.py
paddlehub/compat/datasets/__init__.py
paddlehub/compat/datasets/base_dataset.py
paddlehub/compat/datasets/couplet.py
paddlehub/compat/datasets/nlp_dataset.py
paddlehub/compat/module/__init__.py
paddlehub/compat/module/module_desc_pb2.py
paddlehub/compat/module/module_v1.py
paddlehub/compat/module/module_v1_utils.py
paddlehub/compat/module/nlp_module.py
paddlehub/compat/module/processor.py
paddlehub/compat/task/__init__.py
paddlehub/compat/task/base_task.py
paddlehub/compat/task/batch.py
paddlehub/compat/task/checkpoint.py
paddlehub/compat/task/checkpoint_pb2.py
paddlehub/compat/task/config.py
paddlehub/compat/task/hook.py
paddlehub/compat/task/metrics.py
paddlehub/compat/task/reader.py
paddlehub/compat/task/task_utils.py
paddlehub/compat/task/text_generation_task.py
paddlehub/compat/task/tokenization.py
paddlehub/compat/task/transformer_emb_task.py
paddlehub/datasets/__init__.py
paddlehub/datasets/base_audio_dataset.py
paddlehub/datasets/base_nlp_dataset.py
paddlehub/datasets/base_seg_dataset.py
paddlehub/datasets/canvas.py
paddlehub/datasets/chnsenticorp.py
paddlehub/datasets/esc50.py
paddlehub/datasets/flowers.py
paddlehub/datasets/lcqmc.py
paddlehub/datasets/minicoco.py
paddlehub/datasets/msra_ner.py
