Metadata-Version: 2.1
Name: hub-li
Version: 2.2.1
Summary: A toolkit for managing pretrained models of PaddlePaddle and helping user getting started with transfer learning more efficiently.
Home-page: https://github.com/PaddlePaddle/PaddleHub
Author: li
Author-email: 2462633467@qq.com
License: Apache 2.0
Keywords: paddlehub_li paddlepaddle fine-tune transfer-learning
Platform: UNKNOWN
Classifier: Development Status :: 4 - Beta
Classifier: Intended Audience :: Developers
Classifier: Intended Audience :: Education
Classifier: Intended Audience :: Science/Research
Classifier: License :: OSI Approved :: Apache Software License
Classifier: Programming Language :: Python :: 3.6
Classifier: Programming Language :: Python :: 3.7
Classifier: Programming Language :: Python :: 3.8
Classifier: Topic :: Scientific/Engineering
Classifier: Topic :: Scientific/Engineering :: Mathematics
Classifier: Topic :: Scientific/Engineering :: Artificial Intelligence
Classifier: Topic :: Software Development
Classifier: Topic :: Software Development :: Libraries
Classifier: Topic :: Software Development :: Libraries :: Python Modules
License-File: LICENSE
License-File: AUTHORS.md
